clustergraph/ConnectivityPruning.py
clustergraph/EdgeStrategy.py
clustergraph/GraphPruning.py
clustergraph/Metric_distortion_class.py
clustergraph/NodeStrategy.py
clustergraph/__init__.py
clustergraph/c_GraphPreprocess.py
clustergraph/clustergraph.py
clustergraph/distances.py
clustergraph/plot_graph.py
clustergraph/subsampling.py
clustergraph/utils.py
clustergraph-0.3.2.dist-info/LICENSE
clustergraph-0.3.2.dist-info/METADATA
clustergraph-0.3.2.dist-info/WHEEL
clustergraph-0.3.2.dist-info/top_level.txt
clustergraph-0.3.2.dist-info/RECORD
