Metadata-Version: 2.1
Name: clustergraph
Version: 0.3.2
Summary: ClusterGraph is a tool which allows the visualization of a geometric organization of clusters.
Home-page: https://github.com/dioscuri-tda/clustergraph
Author: Mathis Hallier, Davide Gurnari
Author-email: mathis.hallier28@gmail.com
License: MIT license
Keywords: clustergraph
Requires-Python: >=3.6
License-File: LICENSE
Requires-Dist: numpy
Requires-Dist: pandas
Requires-Dist: networkx
Requires-Dist: matplotlib
Requires-Dist: bokeh
Requires-Dist: scikit-learn
Requires-Dist: pot
